<?xml version="1.0" encoding="UTF-8" ?>
<cml:dictionary xmlns:cml="http://www.xml-cml.org/schema"

	xmlns:convention="http://www.xml-cml.org/convention/" xmlns:unit="http://www.xml-cml.org/unit/nonSi/"
	xmlns:unitType="http://www.xml-cml.org/unit/unitType/" xmlns:si="http://www.xml-cml.org/unit/si/"
	xmlns:nonSi="http://www.xml-cml.org/unit/nonSi/" xmlns:cmlx="http://www.xml-cml.org/schema/cmlx"
	xmlns:xhtml="http://www.w3.org/1999/xhtml" xmlns:xsd="http://www.w3.org/2001/XMLSchema"
	xmlns:dc="http://purl.org/dc/elements/1.1/" convention="convention:dictionary"
	title="This is the adapter dictionary for the cmdlinefixed adapter."
	namespace="http://www.xml-cml.org/dictionary/adapter/cmdlinefixed/"
	dictionaryPrefix="fpcmdadap">

	<dc:author>Martin Kruse</dc:author>
	<cml:description>
		<xhtml:p>
			This dictionary defines the only parameter which the
			cmdlinefixed adapter may have. The only parameter-type this adapter
			has defines dictionary entries and the order of those values defines
			their position. Values of those parameter must be of the structure
			"[DEFAULT_DICTIONARY_PREFIX]:[ENTRYID]".
		</xhtml:p>
	</cml:description>

	<cml:entry id="fixedpos.dictref" term="fixedpos.dictref"
		title="Default dictionary prefix and entry id within that dictionary."
		dataType="xsd:string" unitType="unitType:none" units="si:none">
		<cml:definition>
			<xhtml:p>
				Default dictionary prefix and entry id within that
				dictionary.
			</xhtml:p>
		</cml:definition>
		<cml:description>
			<xhtml:p>
				Parameter with this dictref must contain a value with a
				dictionary default prefix and an entryid within that dictionary. The
				value of the corresponding parameter will then be used in the
				corresponding position of the commandline.
			</xhtml:p>
		</cml:description>
	</cml:entry>
</cml:dictionary>