<?xml version="1.0" encoding="UTF-8" standalone="yes"?>
<root xmlns="http://www.mosgrid.de/genericparser">
    <simpl canonicalClassName="de.ukoeln.msml.genericparser.classes.SimpleRootInfo" propertyName="ROOT"/>
    <adv canonicalClassName="de.mosgrid.msml.jaxb.bindings.Cml" propertyName="ROOT">
        <childConfig canonicalClassName="java.util.List" propertyName="module">
            <extensionConfigCollection extensionName="de.ukoeln.msml.genericparser.gui.extension.MSMLListExtension">
                <extensionConfigs val="false" key="isDynamicList"/>
                <extensionConfigs val="0.1" key="version"/>
            </extensionConfigCollection>
            <childConfig canonicalClassName="de.mosgrid.msml.jaxb.bindings.ModuleType" propertyName="[0]">
                <childConfig propertyName="dictRef">
                    <extensionConfigCollection extensionName="de.ukoeln.msml.genericparser.gui.extension.MSMLFixedTextExtension">
                        <extensionConfigs val="compchem:jobList" key="fixedText"/>
                        <extensionConfigs val="0.1" key="version"/>
                    </extensionConfigCollection>
                </childConfig>
            </childConfig>
        </childConfig>
    </adv>
</root>
